Workbook

Sheet Допущения
A1: AFib Monitor — допущения для цены и юнит-экономики
A2: Синий текст — вводимые числа (меняйте их). Жёлтая заливка — главные рычаги и то, что нужно уточнить. Чёрный — формулы. Каждое число с источником в колонке D. Цены — без НДС и таможни.
A3: Показатель | B3: Значение | C3: Единица | D3: Источник / примечание
A4: Курс
A5: Курс доллара США (НБКР) | B5: 87.45 | C5: сом / $ | D5: НБКР, официальный курс на 17.10.2026: 87,4500 сом — nbkr.kg; economist.kg/dengi/2026/10/16/kursy-valyut-17-oktyabrya-2026/
A6: Детали серийного устройства (цена за 1 шт при партии 100+)
A7: Модуль ESP32-S3-MINI-1-N8 (BLE, процессор) | B7: 3.3787 | C7: $ | D7: LCSC C2913206, цена при 100+ шт: $3.3787 (просмотрено 18.10.2026)
A8: Микросхема ЭКГ AD8232ACPZ-R7 | B8: 5.6441 | C8: $ | D8: LCSC C43216, цена при 100+ шт: $5.6441 (просмотрено 18.10.2026)
A9: Аккумулятор LiPo 3.7 В 150 мА·ч | B9: 5.95 | C9: $ | D9: Adafruit #1317, розница за 1 шт: $5.95 — верхняя граница, оптом дешевле
A10: Остальные детали платы, сама плата и сборка (лист «Плата и сборка») | B10: ='Плата и сборка'!$B$31 -> 1.855 | C10: $ | D10: Считается на листе «Плата и сборка» по ценам LCSC и тарифам JLCPCB. Корпус и кабель к электродам НЕ включены — нет данных.
A11: Расходники
A12: Одноразовый электрод ЭКГ (3M Red Dot 2560) | B12: 0.22 | C12: $ / шт | D12: Tiger Medical: коробка 1000 шт $229.20, «$0.22 per piece» (просмотрено 18.10.2026)
A13: Электродов в месяц на одного пациента | B13: 45 | C13: шт | D13: ДОПУЩЕНИЕ: 3 электрода, смена раз в 2 дня при постоянном ношении. Проверить на стенде и с пациентами.
A14: Сервер и магазины приложений
A15: Сервер Render (самый дешёвый платный) | B15: 7 | C15: $ / мес | D15: render.com/pricing: «$7/month, 512 MB RAM»
A16: База Render Postgres (самая дешёвая платная) | B16: 6 | C16: $ / мес | D16: render.com/pricing: «$6/month, 256 MB RAM». Альтернатива — Neon: бесплатный план 0 $, платный без минимума (neon.com/pricing)
A17: Apple Developer Program | B17: 99 | C17: $ / год | D17: developer.apple.com/programs: «$99 annual membership»
A18: Google Play, регистрация (разово) | B18: 25 | C18: $ | D18: support.google.com/googleplay/android-developer/answer/6112435: «US$25 one-time registration fee»
A19: Комиссия магазина с подписки | B19: 0.15 | D19: Apple Small Business Program: 15% при доходе до $1 млн (developer.apple.com/app-store/small-business-program)
A20: Доля подписок, оплачиваемых через магазин | B20: 1 | D20: ДОПУЩЕНИЕ: 100% (осторожно). Если часть платит напрямую (Mbank, Элсом и т.п.), комиссия меньше.
A21: Наши цены (предложение — проверить опросом 20–30 пациентов и врачей)
A22: Цена устройства | B22: 6900 | C22: сом | D22: ПРЕДЛОЖЕНИЕ: ниже Kardia 6L Max в сомах и примерно 4 суточных Холтера; меняйте
A23: Подписка в месяц (без электродов) | B23: 390 | C23: сом | D23: ПРЕДЛОЖЕНИЕ: меньше 1% средней зарплаты; меняйте
A24: Наценка на электроды, если продаём их пациенту | B24: 0.2 | D24: ПРЕДЛОЖЕНИЕ: электроды продаются отдельно по себестоимости + наценка
A25: Ориентиры рынка
A26: Суточный Холтер — МЦ HUMAN (Бишкек) | B26: 1500 | C26: сом | D26: med.human.kg/holter-ekg: «Суточное холтеровское мониторирование ЭКГ — 1500 сом»
A27: Суточный Холтер — kardiocentr.kg (Бишкек) | B27: 1800 | C27: сом | D27: kardiocentr.kg/czeny: «Суточное ЭКГ-мониторирование (Холтер) — 1800 сом»
A28: Консультация кардиолога (первичная) — kardiocentr.kg | B28: 1300 | C28: сом | D28: kardiocentr.kg/czeny
A29: ЭКГ — kardiocentr.kg | B29: 700 | C29: сом | D29: kardiocentr.kg/czeny
A30: KardiaMobile 6L Max (AliveCor, США) | B30: 149 | C30: $ | D30: kardia.com/products/kardiamobile-6l-max: «$149.00»
A31: KardiaCare Plus, подписка | B31: 199 | C31: $ / год | D31: kardia.com/products/kardiacareplus: «$199/year»
A32: Средняя зарплата в Кыргызстане (янв–май 2026) | B32: 51888 | C32: сом / мес | D32: Нацстатком через economist.kg, 15.07.2026: «51 тысячи 888 сомов»
A33: Постоянное население на начало 2026 | B33: 7404000 | C33: чел. | D33: Нацстатком (демографический ежегодник) через economist.kg, 05.10.2026
A34: Население 65+ на начало 2026 | B34: 475000 | C34: чел. | D34: economist.kg, 05.10.2026: «6.4%, или более 475 тысяч человек»
A35: Распространённость ФП у взрослых (нижняя оценка) | B35: 0.02 | D35: «AF is estimated to affect 2-4% of the adult population worldwide» — Lancet Reg Health West Pac 2022 (PMC9252928), со ссылкой на ESC 2020. Для КР своих данных не нашёл.

Sheet Плата и сборка
A1: Плата и сборка: детали (LCSC) и сборка (JLCPCB, Economic PCBA)
A2: Цены деталей — за 1 шт при ~100 шт (если нет тарифа 100+ — ближайший). Пайки — по числу выводов корпуса, ОЦЕНКА: проверить по футпринтам. Главные детали (ESP32, AD8232, аккумулятор) — на листе «Допущения».
A3: Деталь | B3: Номер LCSC | C3: Кол-во | D3: Цена, $ | E3: Паек на шт | F3: Сумма, $ | G3: Источник / примечание
A4: Зарядка LiPo MCP73831T-2ACI/OT | B4: C424093 | C4: 1 | D4: 0.4483 | E4: 5 | F4: =C4*D4 -> 0.4483 | G4: lcsc.com/product-detail/C424093.html, 100+: $0.4483
A5: Стабилизатор 3.3 В ME6211C33M5G-N | B5: C82942 | C5: 1 | D5: 0.0503 | E5: 5 | F5: =C5*D5 -> 0.0503 | G5: lcsc.com/product-detail/C82942.html, 100+: $0.0503
A6: Разъём USB-C TYPE-C-31-M-12 (16 конт.) | B6: C165948 | C6: 1 | D6: 0.1368 | E6: 20 | F6: =C6*D6 -> 0.1368 | G6: lcsc.com/product-detail/C165948.html, 50+: $0.1368 (тарифа 100+ нет)
A7: Гнездо 3.5 мм для кабеля электродов KH-PJ-321A-SMT | B7: C5123133 | C7: 1 | D7: 0.0819 | E7: 5 | F7: =C7*D7 -> 0.0819 | G7: lcsc.com/product-detail/C5123133.html, 50+: $0.0819 (большая из двух цен)
A8: Разъём аккумулятора JST B2B-PH-K-S (выводной) | B8: C131337 | C8: 1 | D8: 0.0358 | E8: 2 | F8: =C8*D8 -> 0.0358 | G8: lcsc.com/product-detail/C131337.html, 20+: $0.0358; паяется вручную
A9: Резисторы 0402 (обвязка AD8232, делитель батареи, светодиод) | B9: C25744 | C9: 12 | D9: 0.0016 | E9: 2 | F9: =C9*D9 -> 0.0192 | G9: lcsc.com/product-detail/C25744.html, 100+: $0.0016. Количество — ОЦЕНКА по типовой схеме AD8232
A10: Конденсаторы 0402 100 нФ и др. | B10: C1525 | C10: 14 | D10: 0.004 | E10: 2 | F10: =C10*D10 -> 0.056 | G10: lcsc.com/product-detail/C1525.html, 100+: $0.004. Количество — ОЦЕНКА
A11: ESP32-S3-MINI-1 и AD8232 (пайки; цены — на листе «Допущения») | C11: 1 | E11: 86 | G11: ОЦЕНКА: 65 площадок модуля + 21 у AD8232 (LFCSP-20 + теплоотвод); проверить по футпринтам
A13: Цена 5 плат 2 слоя до 100×100 мм (акция) | B13: 2 | G13: lcsc.com/pcba/price: «1-2 layer, 100x100mm … the pcb cost is $2»; для партии 100 шт уточнить калькулятором
A14: Плат в партии | B14: 100 | G14: Меняйте
A15: Типов «Extended»-деталей (за каждый — загрузка питателя) | B15: 6 | G15: Допущение: ESP32, AD8232, MCP73831, USB-C, гнездо 3.5 мм, ME6211 — все Extended
A16: SMT-пайка, $ за пайку (Economic) | B16: 0.0016 | G16: jlcpcb.com/help/article/pcb-assembly-price: 1–100 000 паек
A17: Ручная сборка, $ за пайку | B17: 0.0164 | G17: там же: 1–10 000 паек
A18: Наладка (Economic), за заказ | B18: 8.18 | G18: там же
A19: Трафарет (Economic), за заказ | B19: 1.53 | G19: там же
A20: Загрузка питателя за Extended-деталь | B20: 3.07 | G20: там же: «$3.07 for Extended»
A21: Ручная пайка, за заказ | B21: 3.58 | G21: там же: «Hand-soldering labor $3.58 per order»
A23: Мелкие детали на плату | B23: =SUM(F4:F10) -> 0.8283
A24: Паек SMT на плату | B24: =SUMPRODUCT(C4:C11,E4:E11)-C8*E8 -> 173 | G24: Без выводного разъёма аккумулятора
A25: SMT-пайка на плату | B25: =B24*B16 -> 0.2768
A26: Ручная пайка разъёма на плату | B26: =C8*E8*B17 -> 0.0328
A27: Сама плата, за 1 шт | B27: =B13/5 -> 0.4
A28: Постоянные расходы на партию | B28: =B18+B19+B15*B20+B21 -> 31.71 | G28: Наладка + трафарет + питатели + ручная пайка
A29: Постоянные расходы на 1 плату | B29: =IF(B14=0,0,B28/B14) -> 0.3171
A31: ИТОГО на одну плату (без ESP32, AD8232, аккумулятора, корпуса) | B31: =B23+B25+B26+B27+B29 -> 1.855 | G31: Идёт в «Допущения» → себестоимость устройства

Sheet Юнит-экономика
A1: Юнит-экономика (все суммы в сомах, без НДС и таможни)
A3: Устройство
A4: Себестоимость платы с деталями и сборкой, $ | B4: =Допущения!$B$7+Допущения!$B$8+Допущения!$B$9+Допущения!$B$10 -> 16.8278 | E4: Без корпуса и кабеля к электродам
A5: Себестоимость платы с деталями и сборкой, сом | B5: =B4*Допущения!$B$5 -> 1471.5911
A6: Цена устройства | B6: =Допущения!$B$22 -> 6900
A7: Валовая маржа на устройстве (без корпуса) | B7: =B6-B5 -> 5428.4089 | E7: Завышена на стоимость корпуса, кабеля, упаковки, доставки и пошлин
A8: Маржа, % от цены | B8: =IF(B6=0,0,B7/B6) -> 0.78672593
A10: Подписка — в месяц, по числу подписчиков
A11: Подписчиков | B11: 50 | C11: 200 | D11: 1000 | E11: Сценарии — меняйте числа
A12: Выручка от подписки на 1 подписчика | B12: =Допущения!$B$23 -> 390 | C12: =Допущения!$B$23 -> 390 | D12: =Допущения!$B$23 -> 390
A13: Комиссия магазина на 1 подписчика | B13: =Допущения!$B$23*Допущения!$B$19*Допущения!$B$20 -> 58.5 | C13: =Допущения!$B$23*Допущения!$B$19*Допущения!$B$20 -> 58.5 | D13: =Допущения!$B$23*Допущения!$B$19*Допущения!$B$20 -> 58.5
A14: Сервер + база на 1 подписчика | B14: =(Допущения!$B$15+Допущения!$B$16)*Допущения!$B$5/B11 -> 22.737 | C14: =(Допущения!$B$15+Допущения!$B$16)*Допущения!$B$5/C11 -> 5.68425 | D14: =(Допущения!$B$15+Допущения!$B$16)*Допущения!$B$5/D11 -> 1.13685 | E14: Постоянные $13/мес делятся на всех
A15: Магазины приложений на 1 подписчика | B15: =(Допущения!$B$17/12)*Допущения!$B$5/B11 -> 14.42925 | C15: =(Допущения!$B$17/12)*Допущения!$B$5/C11 -> 3.6073125 | D15: =(Допущения!$B$17/12)*Допущения!$B$5/D11 -> 0.7214625 | E15: Apple $99/год; Google $25 разово не включён
A16: Вклад 1 подписчика в месяц (без электродов) | B16: =B12-B13-B14-B15 -> 294.33375 | C16: =C12-C13-C14-C15 -> 322.20844 | D16: =D12-D13-D14-D15 -> 329.64169 | E16: Сколько остаётся на зарплаты, поддержку, регистрацию
A17: Вклад всех подписчиков в месяц | B17: =B16*B11 -> 14716.688 | C17: =C16*C11 -> 64441.688 | D17: =D16*D11 -> 329641.69
A18: Вклад всех подписчиков в год | B18: =B17*12 -> 176600.25 | C18: =C17*12 -> 773300.25 | D18: =D17*12 -> 3955700.2
A20: Электроды — главный расход
A21: Электроды на 1 пациента в месяц, себестоимость | B21: =Допущения!$B$12*Допущения!$B$13*Допущения!$B$5 -> 865.755 | E21: Больше самой подписки при постоянном ношении — см. вывод
A22: Цена набора электродов на месяц для пациента | B22: =B21*(1+Допущения!$B$24) -> 1038.906 | E22: Если продаём отдельно с наценкой
A23: Себестоимость электродов / подписка | B23: =IF(Допущения!$B$23=0,0,B21/Допущения!$B$23) -> 2.2198846
A24: Итого пациент платит в месяц (подписка + электроды) | B24: =Допущения!$B$23+B22 -> 1428.906
A25: То же, % от средней зарплаты | B25: =IF(Допущения!$B$32=0,0,B24/Допущения!$B$32) -> 0.027538275
A27: Точка безубыточности по постоянным расходам сервиса
A28: Постоянные расходы сервиса в месяц | B28: =(Допущения!$B$15+Допущения!$B$16+Допущения!$B$17/12)*Допущения!$B$5 -> 1858.3125
A29: Вклад 1 подписчика до постоянных расходов | B29: =Допущения!$B$23*(1-Допущения!$B$19*Допущения!$B$20) -> 331.5
A30: Подписчиков, чтобы окупить сервер и магазины | B30: =IF(B29<=0,0,ROUNDUP(B28/B29,0)) -> 6 | E30: Без зарплат, регистрации, маркетинга

Sheet Сравнение
A1: Что платит пациент за год (сом)
A3: Вариант | B3: Первый год | C3: % средней зарплаты за год | D3: Что получает
A4: AFib Monitor: устройство + 12 мес подписки + электроды | B4: =Допущения!$B$22+12*'Юнит-экономика'!B24 -> 24046.872 | C4: =IF(Допущения!$B$32=0,0,B4/(12*Допущения!$B$32)) -> 0.038619835 | D4: Постоянное наблюдение, проверка 30 с, отчёт врачу
A5: AFib Monitor без постоянного ношения (электроды не нужны каждый день) | B5: =Допущения!$B$22+12*Допущения!$B$23 -> 11580 | C5: =IF(Допущения!$B$32=0,0,B5/(12*Допущения!$B$32)) -> 0.018597749 | D5: Если носить только при симптомах — проверить, сколько реально электродов
A6: Суточный Холтер 4 раза в год (HUMAN) | B6: =4*Допущения!$B$26 -> 6000 | C6: =IF(Допущения!$B$32=0,0,B6/(12*Допущения!$B$32)) -> 0.0096361394 | D6: 4 суток наблюдения в год
A7: Суточный Холтер 4 раза в год (kardiocentr.kg) | B7: =4*Допущения!$B$27 -> 7200 | C7: =IF(Допущения!$B$32=0,0,B7/(12*Допущения!$B$32)) -> 0.011563367 | D7: 4 суток наблюдения в год
A8: KardiaMobile 6L Max + KardiaCare Plus (цены США) | B8: =(Допущения!$B$30+Допущения!$B$31)*Допущения!$B$5 -> 30432.6 | C8: =IF(Допущения!$B$32=0,0,B8/(12*Допущения!$B$32)) -> 0.048875463 | D8: Запись ЭКГ по требованию; цены США без доставки и пошлин — сравнение только по цене
A11: Размер рынка — грубо
A12: Людей 65+ с ФП, если доля как у взрослых в мире (нижняя оценка 2%) | B12: =Допущения!$B$34*Допущения!$B$35 -> 9500 | D12: Занижено: у пожилых ФП встречается чаще, чем у взрослых в среднем; данных по КР не нашёл
A13: Подписчиков для окупаемости сервера (из «Юнит-экономики») | B13: ='Юнит-экономика'!B30 -> 6

Sheet Чего не хватает
A1: Чего не хватает для полной себестоимости
A3: Что | B3: Почему важно | C3: Кто
A4: Корпус и кабель к электродам; точная цена платы для 100 шт | B4: Плата и сборка посчитаны по тарифам, но корпус не посчитан; цена самой платы взята как акция $2 за 5 шт | C4: Я: схема в KiCad → калькулятор JLCPCB; корпус — 3D-печать или литьё
A5: Регистрация медизделия в ЕАЭС / КР: класс, сроки, стоимость испытаний | B5: Без регистрации — только wellness-формулировки; это главная статья затрат и срок выхода | C5: Юрист / регулятор (ДЛОиМТ МЗ КР) — нужен человек
A6: Таможня и НДС на ввоз деталей и устройств | B6: Цены в файле без НДС и пошлин | C6: Таможенный брокер / бухгалтер
A7: Налоговый режим ИП (патент / единый налог) | B7: Влияет на чистую прибыль | C7: Бухгалтер
A8: Сколько электродов реально уходит в месяц | B8: Главный расход; допущение 45 шт — не измерено | C8: Стенд + 5–10 пациентов
A9: Цена электродов у местных поставщиков (Бишкек, Гуанчжоу) | B9: Может быть заметно ниже $0.22 | C9: Вы: поставщики в Гуанчжоу
A10: Готовность платить: опрос пациентов и кардиологов | B10: Цены 6 900 сом и 390 сом/мес — предложение, не проверено | C10: Вы + я (анкета)
